globalsearch/control/__init__.py
globalsearch/control/gs_prepare.py
globalsearch/rnaseq/__init__.py
globalsearch/rnaseq/find_files.py
globalsearch/rnaseq/index_star.py
globalsearch/rnaseq/make_kallisto_job.py
globalsearch/rnaseq/make_star_idx_job.py
globalsearch/rnaseq/make_star_salmon_job.py
globalsearch/rnaseq/post_star_salmon.py
globalsearch/rnaseq/run_kallisto.py
globalsearch/rnaseq/run_spladder.py
globalsearch/rnaseq/run_star_salmon.py
globalsearch/rnaseq/trim_galore.py
globalsearch-0.3.1.data/scripts/gs_prepare
globalsearch-0.3.1.data/scripts/gs_submit
globalsearch-0.3.1.dist-info/METADATA
globalsearch-0.3.1.dist-info/WHEEL
globalsearch-0.3.1.dist-info/top_level.txt
globalsearch-0.3.1.dist-info/RECORD
