Metadata-Version: 2.1
Name: globalsearch
Version: 0.3.1
Summary: globalsearch is a collection of Python modules and command tools for the Global Search pipeline.
Home-page: https://github.com/baliga-lab/Global_Search
Author: Wei-ju Wu
Author-email: weiju.wu@gmail.com
Maintainer: Wei-ju Wu
Maintainer-email: weiju.wu@gmail.com
License: LGPL V3
Keywords: global search,coral reef,rna sequencing
Classifier: Development Status :: 4 - Beta
Classifier: Environment :: Console
Classifier: Intended Audience :: Developers
Classifier: Natural Language :: English
Classifier: License :: OSI Approved :: GNU General Public License v3 (GPLv3)
Classifier: Operating System :: OS Independent
Classifier: Programming Language :: Python
Classifier: Programming Language :: Python :: 3
Classifier: Programming Language :: Python :: 3.5
Classifier: Programming Language :: Python :: Implementation :: CPython
Classifier: Topic :: Software Development :: Libraries :: Python Modules
Requires-Dist: jinja2
Requires-Dist: fs
Requires-Dist: rpy2
